pyo_js_turtle/__init__.py
pyo_js_turtle/example.py
pyo_js_turtle-0.1.1.dist-info/LICENSE
pyo_js_turtle-0.1.1.dist-info/METADATA
pyo_js_turtle-0.1.1.dist-info/WHEEL
pyo_js_turtle-0.1.1.dist-info/top_level.txt
pyo_js_turtle-0.1.1.dist-info/RECORD
